LICENSE
MAKEFILE
MANIFEST.in
README.md
setup.py
tox.ini
tests/check-pip-version.py
tests/test.py
tests/test-env-inheritance/tox.ini
tests/test-environment-variable/tox.ini
tests/test-py27/tox.ini
tests/test-two-envs/tox.ini
tests/test-version-specifiers/tox.ini
tox_pip_version/__init__.py
tox_pip_version/hooks.py
tox_pip_version.egg-info/PKG-INFO
tox_pip_version.egg-info/SOURCES.txt
tox_pip_version.egg-info/dependency_links.txt
tox_pip_version.egg-info/entry_points.txt
tox_pip_version.egg-info/requires.txt
tox_pip_version.egg-info/top_level.txt